[
  {
    "lastReplyOrigin": null,
    "oldComplainId": null,
    "additionalFields": null,
    "moderationUserName": "****",
    "companyName": "Vans do Brasil - Loja Online",
    "otherProblemType": null,
    "solved": false,
    "dealAgain": null,
    "otherProductType": null,
    "titleMasked": "Produto descosturou ",
    "type": null,
    "evaluation": null,
    "score": null,
    "userState": "SP",
    "userRequestedDelete": false,
    "requesterName": null,
    "additionalInfo": null,
    "modified": "2025-04-27T17:19:40",
    "logo": null,
    "id": "6lUceK69LuuxPM_4",
    "evaluated": false,
    "presence": "STORE_ON",
    "publishedEmailSent": null,
    "deletionReason": "****",
    "read": true,
    "marketplaceComplain": null,
    "created": "2025-04-27T17:19:28",
    "maskingStatus": "MASKED",
    "ip": "****",
    "moderationReasonDescription": "****",
    "frozen": false,
    "requestEvaluation": null,
    "moderateReason": null,
    "deletedDate": null,
    "files": null,
    "problemType": "0000000000001458",
    "deletedIp": "****",
    "companyIndexes": [
      "{averageAnswerTime=1257655.8010948906, finalScore=7.0, totalNotAnswered=29, totalComplains=2773, consumerScore=5.21, created=2025-04-27T12:00:27, start=2024-10-01T00:00:00, solvedPercentual=76.7, type=SIX_MONTHS, totalAnswered=2740, totalComplains30=539, averageAnswerTime3M=1278384.9528501055, hasStamp=false, dealAgainPercentual=59.5, totalEvaluated=1087, answeredPercentual=98.8, company=190510, end=2025-03-31T23:59:59, id=edf03c1a-b702-45a0-b0d9-f45fd09eb803, status=GOOD}",
      "{averageAnswerTime=1092804.020379147, finalScore=7.7, totalNotAnswered=29, totalComplains=4255, consumerScore=6.27, created=2025-04-27T12:00:27, start=2024-04-01T00:00:00, solvedPercentual=83.8, type=TWELVE_MONTHS, totalAnswered=4220, totalComplains30=539, averageAnswerTime3M=1278384.9528501055, hasStamp=false, dealAgainPercentual=68.4, totalEvaluated=1865, answeredPercentual=99.2, company=190510, end=2025-03-31T23:59:59, id=fa3f7ab8-4cbb-417c-80e9-b5cbaf0581f9, status=GOOD}",
      "{averageAnswerTime=982910.3272519954, finalScore=8.0, totalNotAnswered=0, totalComplains=3513, consumerScore=6.68, created=2025-04-27T12:00:27, start=2024-01-01T00:00:00, solvedPercentual=87.3, type=LAST_YEAR, totalAnswered=3508, totalComplains30=539, averageAnswerTime3M=1278384.9528501055, hasStamp=false, dealAgainPercentual=70.7, totalEvaluated=1730, answeredPercentual=99.9, company=190510, end=2024-12-31T23:59:59, id=1a335b98-e125-40fb-b405-cf643d5bedc5, status=GREAT}",
      "{averageAnswerTime=823695.4580896687, finalScore=7.8, totalNotAnswered=0, totalComplains=2570, consumerScore=6.22, created=2025-04-27T12:00:27, start=2023-01-01T00:00:00, solvedPercentual=87.3, type=PAST_LAST_YEAR, totalAnswered=2565, totalComplains30=539, averageAnswerTime3M=1278384.9528501055, hasStamp=false, dealAgainPercentual=63.7, totalEvaluated=1185, answeredPercentual=99.8, company=190510, end=2023-12-31T23:59:59, id=844adfad-b071-48c4-a81f-9e779bcdc741, status=GOOD}",
      "{averageAnswerTime=1014979.8455551902, finalScore=7.6, totalNotAnswered=279, totalComplains=9416, consumerScore=6.13, created=2025-04-27T12:00:27, start=2022-04-28T00:00:00, solvedPercentual=84.7, type=LAST_THREE_YEARS, totalAnswered=9123, totalComplains30=539, averageAnswerTime3M=1278384.9528501055, hasStamp=false, dealAgainPercentual=64.3, totalEvaluated=3997, answeredPercentual=96.9, company=190510, end=2025-04-27T23:59:59, id=4921f333-6190-4b5b-ad61-c9a2cde323f6, status=GOOD}"
    ],
    "status": "PENDING",
    "companyShortname": "vans-do-brasil-loja-online",
    "userCity": "São Paulo",
    "indexable": null,
    "description": "Comprei um tênis na Authentic Feet, no mês de Outubro/2024. Usei pouquíssimas vezes, o tênis está em ótimo estado, porém a costura",
    "phones": null,
    "title": "Produto descosturou ",
    "interactions": [],
    "complainOrigin": null,
    "firstInteractionDate": null,
    "hasReply": false,
    "compliment": false,
    "legacyId": 215726643,
    "company": "190510",
    "userEmail": "****",
    "productType": "0000000000000347",
    "address": "****",
    "canBeEvaluated": null,
    "userName": "****",
    "url": "produto-descosturou_6lUceK69LuuxPM_4",
    "inModeration": false,
    "moderateRequested": null,
    "deleted": false,
    "complainMediaInfos": [],
    "fantasyName": "Vans do Brasil - Loja Online",
    "category": "0000000000000224",
    "descriptionMasked": "Comprei um tênis na Authentic Feet, no mês de Outubro/2024. Usei pouquíssimas vezes, o tênis está em ótimo estado, porém a costura soltou completamente. <br /><br />",
    "user": null
  },
  {
    "lastReplyOrigin": null,
    "oldComplainId": null,
    "additionalFields": null,
    "moderationUserName": "****",
    "companyName": "Jaé",
    "otherProblemType": null,
    "solved": false,
    "dealAgain": null,
    "otherProductType": null,
    "titleMasked": "Demora na emissão do cartão Jaé Visa ",
    "type": null,
    "evaluation": null,
    "score": null,
    "userState": "RJ",
    "userRequestedDelete": false,
    "requesterName": null,
    "additionalInfo": null,
    "modified": "2025-04-27T17:19:39",
    "logo": null,
    "id": "aqceeqluu8M56nTg",
    "evaluated": false,
    "presence": "SERVICE_ON",
    "publishedEmailSent": null,
    "deletionReason": "****",
    "read": true,
    "marketplaceComplain": null,
    "created": "2025-04-27T17:19:28",
    "maskingStatus": "MASKED",
    "ip": "****",
    "moderationReasonDescription": "****",
    "frozen": false,
    "requestEvaluation": null,
    "moderateReason": null,
    "deletedDate": null,
    "files": null,
    "problemType": "0000000000000001",
    "deletedIp": "****",
    "companyIndexes": [
      "{averageAnswerTime=3282479.8095238097, finalScore=1.8, totalNotAnswered=2138, totalComplains=2668, consumerScore=1.61, created=2025-04-27T09:45:43, start=2024-10-01T00:00:00, solvedPercentual=26.1, type=SIX_MONTHS, totalAnswered=105, totalComplains30=520, averageAnswerTime3M=736205.947368421, hasStamp=false, dealAgainPercentual=22.1, totalEvaluated=475, answeredPercentual=3.9, company=WFQjGnxqw4dtGHUj, end=2025-03-31T23:59:59, id=0a1fa8be-d5d9-4640-a262-0b1aa31fb461, status=NOT_RECOMMENDED}",
      "{averageAnswerTime=2621596.485380117, finalScore=2.1, totalNotAnswered=2139, totalComplains=2742, consumerScore=1.97, created=2025-04-27T09:45:43, start=2024-04-01T00:00:00, solvedPercentual=29.4, type=TWELVE_MONTHS, totalAnswered=171, totalComplains30=520, averageAnswerTime3M=736205.947368421, hasStamp=false, dealAgainPercentual=24.8, totalEvaluated=524, answeredPercentual=6.2, company=WFQjGnxqw4dtGHUj, end=2025-03-31T23:59:59, id=319e5b08-2198-4894-9bcb-86159d7c97b0, status=NOT_RECOMMENDED}",
      "{averageAnswerTime=2738863.953642384, finalScore=3.2, totalNotAnswered=482, totalComplains=771, consumerScore=3.0, created=2025-04-27T09:45:43, start=2024-01-01T00:00:00, solvedPercentual=42.6, type=LAST_YEAR, totalAnswered=151, totalComplains30=520, averageAnswerTime3M=736205.947368421, hasStamp=false, dealAgainPercentual=33.5, totalEvaluated=230, answeredPercentual=19.6, company=WFQjGnxqw4dtGHUj, end=2024-12-31T23:59:59, id=02d940f0-a8db-4899-89f4-450d5756ad6a, status=NOT_RECOMMENDED}",
      "{averageAnswerTime=285134.36363636365, finalScore=7.0, totalNotAnswered=0, totalComplains=11, consumerScore=5.6, created=2025-04-27T09:45:43, start=2023-01-01T00:00:00, solvedPercentual=90.0, type=PAST_LAST_YEAR, totalAnswered=11, totalComplains30=520, averageAnswerTime3M=736205.947368421, hasStamp=false, dealAgainPercentual=30.0, totalEvaluated=10, answeredPercentual=100.0, company=WFQjGnxqw4dtGHUj, end=2023-12-31T23:59:59, id=64f2bc85-0b05-46b2-bb8c-a460a616ac38, status=GOOD}",
      "{averageAnswerTime=1777669.2817869417, finalScore=2.6, totalNotAnswered=2415, totalComplains=3202, consumerScore=2.62, created=2025-04-27T09:45:43, start=2022-04-28T00:00:00, solvedPercentual=36.0, type=LAST_THREE_YEARS, totalAnswered=291, totalComplains30=520, averageAnswerTime3M=736205.947368421, hasStamp=false, dealAgainPercentual=29.3, totalEvaluated=644, answeredPercentual=9.1, company=WFQjGnxqw4dtGHUj, end=2025-04-27T23:59:59, id=65c12f2a-0d80-484c-b0da-e1b85f4d2c88, status=NOT_RECOMMENDED}"
    ],
    "status": "PENDING",
    "companyShortname": "jae-rj",
    "userCity": "Rio de Janeiro",
    "indexable": null,
    "description": "Prezado(a),<br /><br />Gostaria de saber sobre a emissão do meu cartão Jaé Visa (pedido n *****). Fiz a solicitação em ***** e, at",
    "phones": null,
    "title": "Demora na emissão do cartão Jaé Visa ",
    "interactions": [],
    "complainOrigin": null,
    "firstInteractionDate": null,
    "hasReply": false,
    "compliment": false,
    "legacyId": 215726641,
    "company": "WFQjGnxqw4dtGHUj",
    "userEmail": "****",
    "productType": "0000000000001409",
    "address": "****",
    "canBeEvaluated": null,
    "userName": "****",
    "url": "demora-na-emissao-do-cartao-jae-visa_aqceeqluu8M56nTg",
    "inModeration": false,
    "moderateRequested": null,
    "deleted": false,
    "complainMediaInfos": [],
    "fantasyName": "Jaé",
    "category": "0000000000000311",
    "descriptionMasked": "Prezado(a),<br /><br />Gostaria de saber sobre a emissão do meu cartão Jaé Visa (pedido n *****). Fiz a solicitação em ***** e, até o momento, consta apenas como &quot;em produção&quot;, sem qualquer atualização sobre a finalização do processo. Já mandei e-mail pedindo informações sobre, mas não obtive resposta.<br /><br />Gostaria de saber se há previsão para a conclusão e envio do cartão, por favor.<br /><br />Obrigada pela atenção!<br /><br />Atenciosamente,<br />*****",
    "user": null
  },
  {
    "lastReplyOrigin": null,
    "oldComplainId": null,
    "additionalFields": null,
    "moderationUserName": "****",
    "companyName": "iFood",
    "otherProblemType": null,
    "solved": false,
    "dealAgain": null,
    "otherProductType": null,
    "titleMasked": "Pedido do mc",
    "type": null,
    "evaluation": null,
    "score": null,
    "userState": "SP",
    "userRequestedDelete": false,
    "requesterName": null,
    "additionalInfo": null,
    "modified": "2025-04-27T17:19:38",
    "logo": null,
    "id": "ZQ_P9A_uXafj2btC",
    "evaluated": false,
    "presence": "SERVICE_ON",
    "publishedEmailSent": null,
    "deletionReason": "****",
    "read": true,
    "marketplaceComplain": null,
    "created": "2025-04-27T17:19:27",
    "maskingStatus": "MASKED",
    "ip": "****",
    "moderationReasonDescription": "****",
    "frozen": false,
    "requestEvaluation": null,
    "moderateReason": null,
    "deletedDate": null,
    "files": null,
    "problemType": "0000000000000164",
    "deletedIp": "****",
    "companyIndexes": [
      "{averageAnswerTime=485289.3040501575, finalScore=7.5, totalNotAnswered=789, totalComplains=136479, consumerScore=6.21, created=2025-04-26T21:49:07, start=2024-10-01T00:00:00, solvedPercentual=73.2, type=SIX_MONTHS, totalAnswered=135254, totalComplains30=25412, averageAnswerTime3M=268290.46384984674, hasStamp=false, dealAgainPercentual=70.7, totalEvaluated=57259, answeredPercentual=99.1, company=38653, end=2025-03-31T23:59:59, id=a9565267-5654-479e-b52e-a6d7db830a10, status=GOOD}",
      "{averageAnswerTime=694952.1234870187, finalScore=7.1, totalNotAnswered=887, totalComplains=268209, consumerScore=5.76, created=2025-04-26T21:49:07, start=2024-04-01T00:00:00, solvedPercentual=68.9, type=TWELVE_MONTHS, totalAnswered=266692, totalComplains30=25412, averageAnswerTime3M=268290.46384984674, hasStamp=false, dealAgainPercentual=66.3, totalEvaluated=114787, answeredPercentual=99.4, company=38653, end=2025-03-31T23:59:59, id=788e968b-9e86-49ba-a250-7e8c44504234, status=GOOD}",
      "{averageAnswerTime=834513.0382605752, finalScore=6.9, totalNotAnswered=614, totalComplains=267020, consumerScore=5.53, created=2025-04-26T21:49:07, start=2024-01-01T00:00:00, solvedPercentual=66.8, type=LAST_YEAR, totalAnswered=265835, totalComplains30=25412, averageAnswerTime3M=268290.46384984674, hasStamp=false, dealAgainPercentual=63.9, totalEvaluated=115690, answeredPercentual=99.6, company=38653, end=2024-12-31T23:59:59, id=94496ce5-5110-4823-80e8-6fc39d9bbf55, status=REGULAR}",
      "{averageAnswerTime=718911.0875518108, finalScore=7.3, totalNotAnswered=13080, totalComplains=253281, consumerScore=6.06, created=2025-04-26T21:49:07, start=2023-01-01T00:00:00, solvedPercentual=74.3, type=PAST_LAST_YEAR, totalAnswered=235472, totalComplains30=25412, averageAnswerTime3M=268290.46384984674, hasStamp=false, dealAgainPercentual=69.1, totalEvaluated=94375, answeredPercentual=93.0, company=38653, end=2023-12-31T23:59:59, id=a1e006ab-f27a-496d-8aa2-5bef05083638, status=GOOD}",
      "{averageAnswerTime=598320.6362816958, finalScore=7.4, totalNotAnswered=15561, totalComplains=803092, consumerScore=6.1, created=2025-04-26T21:49:07, start=2022-04-27T00:00:00, solvedPercentual=73.5, type=LAST_THREE_YEARS, totalAnswered=782163, totalComplains30=25412, averageAnswerTime3M=268290.46384984674, hasStamp=false, dealAgainPercentual=69.2, totalEvaluated=306019, answeredPercentual=97.4, company=38653, end=2025-04-26T23:59:59, id=aeebc118-ed91-4675-963a-6db2e5ec8224, status=GOOD}"
    ],
    "status": "PENDING",
    "companyShortname": "ifood",
    "userCity": "Santo André",
    "indexable": null,
    "description": "realizei um pedido pelo iFood no mc onde o pedido chegou todo molhado pq o líquido vazou do papel onde é fechado o refrigerante, m",
    "phones": null,
    "title": "Pedido do mc",
    "interactions": [],
    "complainOrigin": null,
    "firstInteractionDate": null,
    "hasReply": false,
    "compliment": false,
    "legacyId": 215726639,
    "company": "38653",
    "userEmail": "****",
    "productType": "0000000000001409",
    "address": "****",
    "canBeEvaluated": null,
    "userName": "****",
    "url": "pedido-do-mc_ZQ_P9A_uXafj2btC",
    "inModeration": false,
    "moderateRequested": null,
    "deleted": false,
    "complainMediaInfos": [],
    "fantasyName": "iFood",
    "category": "0000000000000298",
    "descriptionMasked": "realizei um pedido pelo iFood no mc onde o pedido chegou todo molhado pq o líquido vazou do papel onde é fechado o refrigerante, molhou toda a batata e os lanches, Solicitei o reembolso pq ninguém é obrigado a comer lanche molhado, e simplesmente não foi resolvido o problema, nunca mais peço no mc enquanto n mudarem o jeito de enviar o refrigerante, pessima embalagem, não é a primeira vez que o pedido chega molhado!!!!!!!!",
    "user": null
  },
  {
    "lastReplyOrigin": null,
    "oldComplainId": null,
    "additionalFields": null,
    "moderationUserName": "****",
    "companyName": "Serasa",
    "otherProblemType": null,
    "solved": false,
    "dealAgain": null,
    "otherProductType": null,
    "titleMasked": "Cobrança indevida",
    "type": null,
    "evaluation": null,
    "score": null,
    "userState": "SC",
    "userRequestedDelete": false,
    "requesterName": null,
    "additionalInfo": null,
    "modified": "2025-04-27T17:19:37",
    "logo": null,
    "id": "Lj_4Pyw7DMqRrJRN",
    "evaluated": false,
    "presence": "SERVICE_ON",
    "publishedEmailSent": null,
    "deletionReason": "****",
    "read": true,
    "marketplaceComplain": null,
    "created": "2025-04-27T17:19:25",
    "maskingStatus": "MASKED",
    "ip": "****",
    "moderationReasonDescription": "****",
    "frozen": false,
    "requestEvaluation": null,
    "moderateReason": null,
    "deletedDate": null,
    "files": null,
    "problemType": "0000000000001767",
    "deletedIp": "****",
    "companyIndexes": [
      "{averageAnswerTime=189179.60331149626, finalScore=7.3, totalNotAnswered=4106, totalComplains=76822, consumerScore=6.39, created=2025-04-27T07:46:55, start=2024-10-01T00:00:00, solvedPercentual=70.5, type=SIX_MONTHS, totalAnswered=72354, totalComplains30=28324, averageAnswerTime3M=196272.40039254172, hasStamp=false, dealAgainPercentual=66.9, totalEvaluated=24758, answeredPercentual=94.2, company=178670, end=2025-03-31T23:59:59, id=a94a1f6a-929f-445b-9fed-baf15133f5c9, status=GOOD}",
      "{averageAnswerTime=182305.94303132227, finalScore=7.5, totalNotAnswered=4854, totalComplains=138557, consumerScore=6.59, created=2025-04-27T07:46:55, start=2024-04-01T00:00:00, solvedPercentual=72.7, type=TWELVE_MONTHS, totalAnswered=133196, totalComplains30=28324, averageAnswerTime3M=196272.40039254172, hasStamp=false, dealAgainPercentual=69.3, totalEvaluated=48054, answeredPercentual=96.1, company=178670, end=2025-03-31T23:59:59, id=e27cb94b-16d1-4ff6-afa2-b320f12021a1, status=GOOD}",
      "{averageAnswerTime=203625.569125893, finalScore=7.6, totalNotAnswered=2091, totalComplains=124836, consumerScore=6.69, created=2025-04-27T07:46:55, start=2024-01-01T00:00:00, solvedPercentual=74.6, type=LAST_YEAR, totalAnswered=122342, totalComplains30=28324, averageAnswerTime3M=196272.40039254172, hasStamp=false, dealAgainPercentual=70.7, totalEvaluated=45085, answeredPercentual=98.0, company=178670, end=2024-12-31T23:59:59, id=a8cd8a81-fa59-4693-a28d-2e9c9b0a1dfa, status=GOOD}",
      "{averageAnswerTime=434528.84816280386, finalScore=7.8, totalNotAnswered=3319, totalComplains=136672, consumerScore=6.83, created=2025-04-27T07:46:55, start=2023-01-01T00:00:00, solvedPercentual=78.6, type=PAST_LAST_YEAR, totalAnswered=132675, totalComplains30=28324, averageAnswerTime3M=196272.40039254172, hasStamp=false, dealAgainPercentual=72.6, totalEvaluated=39537, answeredPercentual=97.1, company=178670, end=2023-12-31T23:59:59, id=e3e2b9b7-2e3f-41bc-9008-86278b88af01, status=GOOD}",
      "{averageAnswerTime=320517.36273907655, finalScore=7.5, totalNotAnswered=15266, totalComplains=365005, consumerScore=6.65, created=2025-04-27T07:46:55, start=2022-04-28T00:00:00, solvedPercentual=74.8, type=LAST_THREE_YEARS, totalAnswered=348424, totalComplains30=28324, averageAnswerTime3M=196272.40039254172, hasStamp=false, dealAgainPercentual=70.0, totalEvaluated=112149, answeredPercentual=95.5, company=178670, end=2025-04-27T23:59:59, id=dbba9ad4-1746-4c87-bb0c-8da2ec80f6b7, status=GOOD}"
    ],
    "status": "PENDING",
    "companyShortname": "serasa",
    "userCity": "Chapecó",
    "indexable": null,
    "description": "Conforme decisão do STJ, dívida com mais de 5 anos não pode ser cobrada extrajudicialmente. Seja no Serasa ou no registrato. Solic",
    "phones": null,
    "title": "Cobrança indevida",
    "interactions": [],
    "complainOrigin": null,
    "firstInteractionDate": null,
    "hasReply": false,
    "compliment": false,
    "legacyId": 215726637,
    "company": "178670",
    "userEmail": "****",
    "productType": "0000000000000030",
    "address": "****",
    "canBeEvaluated": null,
    "userName": "****",
    "url": "cobranca-indevida_Lj_4Pyw7DMqRrJRN",
    "inModeration": false,
    "moderateRequested": null,
    "deleted": false,
    "complainMediaInfos": [],
    "fantasyName": "Serasa",
    "category": "0000000000000004",
    "descriptionMasked": "Conforme decisão do STJ, dívida com mais de 5 anos não pode ser cobrada extrajudicialmente. Seja no Serasa ou no registrato. Solicito a imediata retirada do meu nome, sob risco de processo judicial.",
    "user": null
  },
  {
    "lastReplyOrigin": null,
    "oldComplainId": null,
    "additionalFields": null,
    "moderationUserName": "****",
    "companyName": "Arno",
    "otherProblemType": "Produto veio com defeito",
    "solved": false,
    "dealAgain": null,
    "otherProductType": "Air FryeR",
    "titleMasked": "Produto defeituoso da Arno e falta de suporte adequado!",
    "type": null,
    "evaluation": null,
    "score": null,
    "userState": "SC",
    "userRequestedDelete": false,
    "requesterName": null,
    "additionalInfo": null,
    "modified": "2025-04-27T17:19:35",
    "logo": "https://raichu-uploads.s3.amazonaws.com/company_572600f5-0681-4e02-bd62-d85eeceae839.jpg",
    "id": "A6sQQa7GCWhkurRV",
    "evaluated": false,
    "presence": "MANUFACTURER",
    "publishedEmailSent": null,
    "deletionReason": "****",
    "read": true,
    "marketplaceComplain": null,
    "created": "2025-04-27T17:19:23",
    "maskingStatus": "MASKED",
    "ip": "****",
    "moderationReasonDescription": "****",
    "frozen": false,
    "requestEvaluation": null,
    "moderateReason": null,
    "deletedDate": null,
    "files": null,
    "problemType": null,
    "deletedIp": "****",
    "companyIndexes": [
      "{averageAnswerTime=546167.9987730061, finalScore=8.6, totalNotAnswered=1, totalComplains=1632, consumerScore=7.64, created=2025-04-26T19:37:41, start=2024-10-01T00:00:00, solvedPercentual=90.7, type=SIX_MONTHS, totalAnswered=1630, totalComplains30=361, averageAnswerTime3M=758356.6322517208, hasStamp=true, dealAgainPercentual=80.4, totalEvaluated=728, answeredPercentual=99.9, company=421, end=2025-03-31T23:59:59, id=109532da-618f-4d84-92e0-ce5422632c77, status=RA1000}",
      "{averageAnswerTime=500886.77103448275, finalScore=8.7, totalNotAnswered=1, totalComplains=2902, consumerScore=7.77, created=2025-04-26T19:37:41, start=2024-04-01T00:00:00, solvedPercentual=89.8, type=TWELVE_MONTHS, totalAnswered=2900, totalComplains30=361, averageAnswerTime3M=758356.6322517208, hasStamp=false, dealAgainPercentual=82.2, totalEvaluated=1371, answeredPercentual=99.9, company=421, end=2025-03-31T23:59:59, id=6512d23c-10d1-4a20-9bff-679c4548333f, status=GREAT}",
      "{averageAnswerTime=348751.7853965901, finalScore=8.9, totalNotAnswered=0, totalComplains=2698, consumerScore=8.12, created=2025-04-26T19:37:41, start=2024-01-01T00:00:00, solvedPercentual=92.0, type=LAST_YEAR, totalAnswered=2698, totalComplains30=361, averageAnswerTime3M=758356.6322517208, hasStamp=true, dealAgainPercentual=85.4, totalEvaluated=1416, answeredPercentual=100.0, company=421, end=2024-12-31T23:59:59, id=34d33b6d-4d1d-490c-987b-145e247beec7, status=RA1000}",
      "{averageAnswerTime=450651.9651390521, finalScore=9.0, totalNotAnswered=0, totalComplains=2553, consumerScore=8.34, created=2025-04-26T19:37:41, start=2023-01-01T00:00:00, solvedPercentual=93.9, type=PAST_LAST_YEAR, totalAnswered=2553, totalComplains30=361, averageAnswerTime3M=758356.6322517208, hasStamp=true, dealAgainPercentual=86.4, totalEvaluated=1339, answeredPercentual=100.0, company=421, end=2023-12-31T23:59:59, id=6777b2ac-44ed-45d5-a1bd-763dbd8bf292, status=RA1000}",
      "{averageAnswerTime=476261.29599606973, finalScore=8.9, totalNotAnswered=104, totalComplains=8247, consumerScore=8.23, created=2025-04-26T19:37:41, start=2022-04-27T00:00:00, solvedPercentual=92.9, type=LAST_THREE_YEARS, totalAnswered=8142, totalComplains30=361, averageAnswerTime3M=758356.6322517208, hasStamp=true, dealAgainPercentual=85.7, totalEvaluated=4082, answeredPercentual=98.7, company=421, end=2025-04-26T23:59:59, id=57bc0c65-66e6-4715-a4b7-6769e846a586, status=RA1000}"
    ],
    "status": "PENDING",
    "companyShortname": "arno",
    "userCity": "Itajaí",
    "indexable": null,
    "description": "Comprei uma Air Fryer da marca Arno na loja Havan de *****, no dia 16/03/2025. Após 48 horas da compra, percebi que o produto não ",
    "phones": null,
    "title": "Produto defeituoso da Arno e falta de suporte adequado!",
    "interactions": [],
    "complainOrigin": null,
    "firstInteractionDate": null,
    "hasReply": false,
    "compliment": false,
    "legacyId": 215726635,
    "company": "421",
    "userEmail": "****",
    "productType": null,
    "address": "****",
    "canBeEvaluated": null,
    "userName": "****",
    "url": "produto-defeituoso-da-arno-e-falta-de-suporte-adequado_A6sQQa7GCWhkurRV",
    "inModeration": false,
    "moderateRequested": null,
    "deleted": false,
    "complainMediaInfos": [],
    "fantasyName": "Arno",
    "category": null,
    "descriptionMasked": "Comprei uma Air Fryer da marca Arno na loja Havan de *****, no dia 16/03/2025. Após 48 horas da compra, percebi que o produto não estava funcionando corretamente.<br />Voltei à loja para tentar fazer a troca, mas fui informada que, como já havia passado o prazo de 48 horas, eu deveria procurar a assistência técnica.<br /><br />Fui então encaminhada para a assistência Eletro House, em *****, onde a Air Fryer ficou até o dia 23/04/2025.<br />No entanto, ao utilizar o produto hoje, dia 27/04/2025, ele continuou sem funcionar.<br /><br />Tentei contato com a Arno diversas vezes e não obtive retorno.<br />Agora pergunto: eu é que vou ficar no prejuízo?<br />Comprei um produto novo, confiei na marca e na loja, e até agora não tive meu problema resolvido. Quero uma solução definitiva seja a troca imediata do produto ou a devolução do valor pago.<br /><br />Aguardo um posicionamento urgente!",
    "user": null
  },
  {
    "lastReplyOrigin": null,
    "oldComplainId": null,
    "additionalFields": null,
    "moderationUserName": "****",
    "companyName": "LATAM Airlines",
    "otherProblemType": null,
    "solved": false,
    "dealAgain": null,
    "otherProductType": null,
    "titleMasked": "Obrigatoriedade de despacho",
    "type": null,
    "evaluation": null,
    "score": null,
    "userState": "RO",
    "userRequestedDelete": false,
    "requesterName": null,
    "additionalInfo": null,
    "modified": "2025-04-27T17:19:31",
    "logo": null,
    "id": "Y_DSkvaJwSyNtSOO",
    "evaluated": false,
    "presence": "SERVICE_OFF",
    "publishedEmailSent": null,
    "deletionReason": "****",
    "read": true,
    "marketplaceComplain": null,
    "created": "2025-04-27T17:19:19",
    "maskingStatus": "MASKED",
    "ip": "****",
    "moderationReasonDescription": "****",
    "frozen": false,
    "requestEvaluation": null,
    "moderateReason": null,
    "deletedDate": null,
    "files": null,
    "problemType": "0000000000001463",
    "deletedIp": "****",
    "companyIndexes": [
      "{averageAnswerTime=216872.01339407745, finalScore=7.1, totalNotAnswered=4, totalComplains=21959, consumerScore=6.01, created=2025-04-27T08:58:05, start=2024-10-01T00:00:00, solvedPercentual=66.6, type=SIX_MONTHS, totalAnswered=21950, totalComplains30=2775, averageAnswerTime3M=248714.87286837536, hasStamp=false, dealAgainPercentual=65.6, totalEvaluated=12192, answeredPercentual=100.0, company=277, end=2025-03-31T23:59:59, id=5b671c79-7476-468c-a181-a58253291822, status=GOOD}",
      "{averageAnswerTime=202491.91682178018, finalScore=7.4, totalNotAnswered=4, totalComplains=44600, consumerScore=6.35, created=2025-04-27T08:58:05, start=2024-04-01T00:00:00, solvedPercentual=71.1, type=TWELVE_MONTHS, totalAnswered=44591, totalComplains30=2775, averageAnswerTime3M=248714.87286837536, hasStamp=false, dealAgainPercentual=69.6, totalEvaluated=26838, answeredPercentual=100.0, company=277, end=2025-03-31T23:59:59, id=c9e5f23f-7a0a-4005-a8ef-d4f4ea866431, status=GOOD}",
      "{averageAnswerTime=186849.66385018392, finalScore=7.4, totalNotAnswered=2, totalComplains=44860, consumerScore=6.34, created=2025-04-27T08:58:05, start=2024-01-01T00:00:00, solvedPercentual=71.8, type=LAST_YEAR, totalAnswered=44855, totalComplains30=2775, averageAnswerTime3M=248714.87286837536, hasStamp=false, dealAgainPercentual=69.7, totalEvaluated=27435, answeredPercentual=100.0, company=277, end=2024-12-31T23:59:59, id=87067fb0-cb1c-4170-8926-87e8bcd428a9, status=GOOD}",
      "{averageAnswerTime=513939.08746210806, finalScore=7.1, totalNotAnswered=1, totalComplains=40361, consumerScore=5.69, created=2025-04-27T08:58:05, start=2023-01-01T00:00:00, solvedPercentual=70.0, type=PAST_LAST_YEAR, totalAnswered=40246, totalComplains30=2775, averageAnswerTime3M=248714.87286837536, hasStamp=false, dealAgainPercentual=64.8, totalEvaluated=20150, answeredPercentual=99.7, company=277, end=2023-12-31T23:59:59, id=f2ce13bc-66dd-42b6-8e3c-801617d4086a, status=GOOD}",
      "{averageAnswerTime=428239.89787621895, finalScore=7.2, totalNotAnswered=215, totalComplains=124458, consumerScore=5.89, created=2025-04-27T08:58:05, start=2022-04-28T00:00:00, solvedPercentual=69.6, type=LAST_THREE_YEARS, totalAnswered=123977, totalComplains30=2775, averageAnswerTime3M=248714.87286837536, hasStamp=false, dealAgainPercentual=66.1, totalEvaluated=64706, answeredPercentual=99.6, company=277, end=2025-04-27T23:59:59, id=b5101522-e0dc-4bee-82d7-706f194528ef, status=GOOD}"
    ],
    "status": "PENDING",
    "companyShortname": "latam-airlines-tam",
    "userCity": "Vilhena",
    "indexable": null,
    "description": "E meu marido fomos obrigados a despachar as malas de mão com a justificativa de aeronave cheia. Porém, quando entramos havia vário",
    "phones": null,
    "title": "Obrigatoriedade de despacho",
    "interactions": [],
    "complainOrigin": null,
    "firstInteractionDate": null,
    "hasReply": false,
    "compliment": false,
    "legacyId": 215726633,
    "company": "277",
    "userEmail": "****",
    "productType": "0000000000001197",
    "address": "****",
    "canBeEvaluated": null,
    "userName": "****",
    "url": "obrigatoriedade-de-despacho_Y_DSkvaJwSyNtSOO",
    "inModeration": false,
    "moderateRequested": null,
    "deleted": false,
    "complainMediaInfos": [],
    "fantasyName": "LATAM Airlines",
    "category": "0000000000000018",
    "descriptionMasked": "E meu marido fomos obrigados a despachar as malas de mão com a justificativa de aeronave cheia. Porém, quando entramos havia vários compartimentos vazios. Não gostei do transtorno gerado, pois a bagagem de mão é pra ter acesso rápido a itens de necessidade e esse direito me foi privado. Não gostei do atendimento, foi grosseiro ao usar de sarcasmo e ironia pra me responder quando perguntei como poderia estar lotado se cada cliente tem direito a apenas uma bagagem de mão? Ele respondeu que a Latam apenas usa os aviões não os fábrica.",
    "user": null
  },
  {
    "lastReplyOrigin": null,
    "oldComplainId": null,
    "additionalFields": null,
    "moderationUserName": "****",
    "companyName": "Óticas Gassi",
    "otherProblemType": null,
    "solved": false,
    "dealAgain": null,
    "otherProductType": null,
    "titleMasked": "Garantia não atendida ",
    "type": null,
    "evaluation": null,
    "score": null,
    "userState": "SP",
    "userRequestedDelete": false,
    "requesterName": null,
    "additionalInfo": "",
    "modified": "2025-04-27T17:19:30",
    "logo": null,
    "id": "gXEV9v2JlTAloW2M",
    "evaluated": false,
    "presence": null,
    "publishedEmailSent": null,
    "deletionReason": "****",
    "read": true,
    "marketplaceComplain": null,
    "created": "2025-04-27T17:19:19",
    "maskingStatus": "MASKED",
    "ip": "****",
    "moderationReasonDescription": "****",
    "frozen": false,
    "requestEvaluation": null,
    "moderateReason": null,
    "deletedDate": null,
    "files": null,
    "problemType": "0000000000000016",
    "deletedIp": "****",
    "companyIndexes": [
      "{averageAnswerTime=280299.36041666666, finalScore=8.5, totalNotAnswered=0, totalComplains=480, consumerScore=7.54, created=2025-04-27T07:31:03, start=2024-10-01T00:00:00, solvedPercentual=93.3, type=SIX_MONTHS, totalAnswered=480, totalComplains30=116, averageAnswerTime3M=217541.95901639343, hasStamp=true, dealAgainPercentual=73.1, totalEvaluated=346, answeredPercentual=100.0, company=27085, end=2025-03-31T23:59:59, id=fbe7f7ef-fe4f-4c1c-961d-54c8b1658e21, status=RA1000}",
      "{averageAnswerTime=385188.4651162791, finalScore=8.1, totalNotAnswered=0, totalComplains=1032, consumerScore=7.1, created=2025-04-27T07:31:03, start=2024-04-01T00:00:00, solvedPercentual=87.3, type=TWELVE_MONTHS, totalAnswered=1032, totalComplains30=116, averageAnswerTime3M=217541.95901639343, hasStamp=false, dealAgainPercentual=68.8, totalEvaluated=708, answeredPercentual=100.0, company=27085, end=2025-03-31T23:59:59, id=d4a307f8-bc21-468b-9be5-59c50996e270, status=GREAT}",
      "{averageAnswerTime=411804.9981481481, finalScore=7.8, totalNotAnswered=0, totalComplains=1080, consumerScore=6.73, created=2025-04-27T07:31:03, start=2024-01-01T00:00:00, solvedPercentual=83.8, type=LAST_YEAR, totalAnswered=1080, totalComplains30=116, averageAnswerTime3M=217541.95901639343, hasStamp=false, dealAgainPercentual=62.8, totalEvaluated=722, answeredPercentual=100.0, company=27085, end=2024-12-31T23:59:59, id=0b447c30-8040-474c-bce5-f5e54dc08bca, status=GOOD}",
      "{averageAnswerTime=276105.1725888325, finalScore=8.5, totalNotAnswered=0, totalComplains=985, consumerScore=8.0, created=2025-04-27T07:31:03, start=2023-01-01T00:00:00, solvedPercentual=92.0, type=PAST_LAST_YEAR, totalAnswered=985, totalComplains30=116, averageAnswerTime3M=217541.95901639343, hasStamp=false, dealAgainPercentual=69.4, totalEvaluated=764, answeredPercentual=100.0, company=27085, end=2023-12-31T23:59:59, id=6f36948a-9a65-427b-8d88-bf63e0674659, status=GREAT}",
      "{averageAnswerTime=309701.13858424727, finalScore=8.1, totalNotAnswered=11, totalComplains=3020, consumerScore=7.29, created=2025-04-27T07:31:03, start=2022-04-28T00:00:00, solvedPercentual=87.4, type=LAST_THREE_YEARS, totalAnswered=3009, totalComplains30=116, averageAnswerTime3M=217541.95901639343, hasStamp=false, dealAgainPercentual=64.6, totalEvaluated=2138, answeredPercentual=99.6, company=27085, end=2025-04-27T23:59:59, id=d43ee128-54d6-45b5-beb1-03510d1cea95, status=GREAT}"
    ],
    "status": "PENDING",
    "companyShortname": "gassi",
    "userCity": "São Sebastião",
    "indexable": null,
    "description": "Comprei meus óculos com garantia, a armação não aguentou nem 3 meses, voltei a loja e cumpri todas as exigências para a substituiç",
    "phones": null,
    "title": "Garantia não atendida ",
    "interactions": [],
    "complainOrigin": null,
    "firstInteractionDate": null,
    "hasReply": false,
    "compliment": false,
    "legacyId": 215726631,
    "company": "27085",
    "userEmail": "****",
    "productType": "0000000000000783",
    "address": "****",
    "canBeEvaluated": null,
    "userName": "****",
    "url": "garantia-nao-atendida_gXEV9v2JlTAloW2M",
    "inModeration": false,
    "moderateRequested": null,
    "deleted": false,
    "complainMediaInfos": [],
    "fantasyName": "Óticas Gassi",
    "category": "0000000000000000",
    "descriptionMasked": "Comprei meus óculos com garantia, a armação não aguentou nem 3 meses, voltei a loja e cumpri todas as exigências para a substituição, ficaram de procurar nas lojas um igual e entrar em contato, nunca ligaram. Fui até o loja para escolher outro e a atendente só me deu duas opções para que pudessem aproveitar as lentes, só que eu não gostei de nenhuma das duas. Então mandou que eu aguardasse mais para encontrarem um igual e nada. Resumindo, a armava quebrou no final de fevereiro, se passaram dois meses e não me deram uma solução.",
    "user": null
  },
  {
    "lastReplyOrigin": null,
    "oldComplainId": null,
    "additionalFields": null,
    "moderationUserName": "****",
    "companyName": "Caixa Econômica Federal",
    "otherProblemType": null,
    "solved": false,
    "dealAgain": null,
    "otherProductType": null,
    "titleMasked": "Absurdo",
    "type": null,
    "evaluation": null,
    "score": null,
    "userState": "SP",
    "userRequestedDelete": false,
    "requesterName": null,
    "additionalInfo": null,
    "modified": "2025-04-27T17:19:29",
    "logo": null,
    "id": "s7o5dklg3hN8wlA3",
    "evaluated": false,
    "presence": null,
    "publishedEmailSent": null,
    "deletionReason": "****",
    "read": true,
    "marketplaceComplain": null,
    "created": "2025-04-27T17:19:18",
    "maskingStatus": "MASKED",
    "ip": "****",
    "moderationReasonDescription": "****",
    "frozen": false,
    "requestEvaluation": null,
    "moderateReason": null,
    "deletedDate": null,
    "files": null,
    "problemType": "0000000000000002",
    "deletedIp": "****",
    "companyIndexes": [
      "{averageAnswerTime=4878328.466858667, finalScore=5.5, totalNotAnswered=311, totalComplains=26113, consumerScore=3.92, created=2025-04-27T07:36:15, start=2024-10-01T00:00:00, solvedPercentual=51.0, type=SIX_MONTHS, totalAnswered=23611, totalComplains30=5432, averageAnswerTime3M=2705428.377332759, hasStamp=false, dealAgainPercentual=46.9, totalEvaluated=7008, answeredPercentual=90.4, company=105, end=2025-03-31T23:59:59, id=c53f89cc-1196-4d9b-b5fa-e33f3e4efbe9, status=BAD}",
      "{averageAnswerTime=6900626.344297136, finalScore=4.3, totalNotAnswered=13395, totalComplains=50053, consumerScore=3.31, created=2025-04-27T07:36:15, start=2024-04-01T00:00:00, solvedPercentual=43.4, type=TWELVE_MONTHS, totalAnswered=29643, totalComplains30=5432, averageAnswerTime3M=2705428.377332759, hasStamp=false, dealAgainPercentual=40.0, totalEvaluated=12636, answeredPercentual=59.2, company=105, end=2025-03-31T23:59:59, id=77a9ef92-e63f-4276-8b41-b6ff83ec95c7, status=NOT_RECOMMENDED}",
      "{averageAnswerTime=1.0769961280851614E7, finalScore=3.2, totalNotAnswered=20838, totalComplains=45097, consumerScore=2.69, created=2025-04-27T07:36:15, start=2024-01-01T00:00:00, solvedPercentual=36.1, type=LAST_YEAR, totalAnswered=15453, totalComplains30=5432, averageAnswerTime3M=2705428.377332759, hasStamp=false, dealAgainPercentual=33.2, totalEvaluated=11069, answeredPercentual=34.3, company=105, end=2024-12-31T23:59:59, id=fecffab2-35f6-400e-88dd-3dcd10e87fbe, status=NOT_RECOMMENDED}",
      "{averageAnswerTime=0.0, finalScore=2.4, totalNotAnswered=28040, totalComplains=36297, consumerScore=2.29, created=2025-04-27T07:36:15, start=2023-01-01T00:00:00, solvedPercentual=36.8, type=PAST_LAST_YEAR, totalAnswered=0, totalComplains30=5432, averageAnswerTime3M=2705428.377332759, hasStamp=false, dealAgainPercentual=28.4, totalEvaluated=8257, answeredPercentual=0.0, company=105, end=2023-12-31T23:59:59, id=315ee70b-8d3d-4e0c-b35a-24c7244e98ed, status=NOT_RECOMMENDED}",
      "{averageAnswerTime=6516322.324357676, finalScore=3.3, totalNotAnswered=71895, totalComplains=127154, consumerScore=2.82, created=2025-04-27T07:36:15, start=2022-04-28T00:00:00, solvedPercentual=40.7, type=LAST_THREE_YEARS, totalAnswered=31604, totalComplains30=5432, averageAnswerTime3M=2705428.377332759, hasStamp=false, dealAgainPercentual=34.4, totalEvaluated=29718, answeredPercentual=24.9, company=105, end=2025-04-27T23:59:59, id=ad4e7e47-6597-4aa9-be7a-8ecfd406383e, status=NOT_RECOMMENDED}"
    ],
    "status": "PENDING",
    "companyShortname": "caixa-economica-federal",
    "userCity": "São Paulo",
    "indexable": null,
    "description": "Esse banco é um lixo, acho que ninguém deveria optar por ele, atendimento péssimo, pessoas mal educadas, você não consegue fazer u",
    "phones": null,
    "title": "Absurdo",
    "interactions": [],
    "complainOrigin": null,
    "firstInteractionDate": null,
    "hasReply": false,
    "compliment": false,
    "legacyId": 215726629,
    "company": "105",
    "userEmail": "****",
    "productType": "0000000000000025",
    "address": "****",
    "canBeEvaluated": null,
    "userName": "****",
    "url": "absurdo_s7o5dklg3hN8wlA3",
    "inModeration": false,
    "moderateRequested": null,
    "deleted": false,
    "complainMediaInfos": [],
    "fantasyName": "Caixa Econômica Federal",
    "category": "0000000000000003",
    "descriptionMasked": "Esse banco é um lixo, acho que ninguém deveria optar por ele, atendimento péssimo, pessoas mal educadas, você não consegue fazer uma transferência, sp funciona dia de semana, pq só tem gente preguiçosa, fora que os juros são abusivos, um banco que jamais teria , não indico para ninguém, pois vai se arrepender.",
    "user": null
  },
  {
    "lastReplyOrigin": null,
    "oldComplainId": null,
    "additionalFields": null,
    "moderationUserName": "****",
    "companyName": "Cacau Show",
    "otherProblemType": "Produto veio faltando",
    "solved": false,
    "dealAgain": null,
    "otherProductType": "Ovo de pascoa",
    "titleMasked": null,
    "type": null,
    "evaluation": null,
    "score": null,
    "userState": "SP",
    "userRequestedDelete": false,
    "requesterName": null,
    "additionalInfo": null,
    "modified": "2025-04-27T17:19:16",
    "logo": null,
    "id": "v3KKPjpqplv8HQOO",
    "evaluated": false,
    "presence": "STORE_ON",
    "publishedEmailSent": null,
    "deletionReason": "****",
    "read": true,
    "marketplaceComplain": null,
    "created": "2025-04-27T17:19:15",
    "maskingStatus": "IGNORED",
    "ip": "****",
    "moderationReasonDescription": "****",
    "frozen": false,
    "requestEvaluation": null,
    "moderateReason": null,
    "deletedDate": null,
    "files": null,
    "problemType": null,
    "deletedIp": "****",
    "companyIndexes": [
      "{averageAnswerTime=319290.0, finalScore=1.5, totalNotAnswered=529, totalComplains=653, consumerScore=1.77, created=2025-04-27T10:04:09, start=2024-10-01T00:00:00, solvedPercentual=20.2, type=SIX_MONTHS, totalAnswered=1, totalComplains30=450, averageAnswerTime3M=319290.0, hasStamp=false, dealAgainPercentual=17.7, totalEvaluated=124, answeredPercentual=0.2, company=YrngerqO28rR2QX4, end=2025-03-31T23:59:59, id=9927c492-e8f3-49f2-96b1-4d48284fb14b, status=NOT_RECOMMENDED}",
      "{averageAnswerTime=319290.0, finalScore=1.5, totalNotAnswered=537, totalComplains=662, consumerScore=1.76, created=2025-04-27T10:04:09, start=2024-04-01T00:00:00, solvedPercentual=20.0, type=TWELVE_MONTHS, totalAnswered=1, totalComplains30=450, averageAnswerTime3M=319290.0, hasStamp=false, dealAgainPercentual=17.6, totalEvaluated=125, answeredPercentual=0.2, company=YrngerqO28rR2QX4, end=2025-03-31T23:59:59, id=c73bf039-55ed-49ba-b479-cc9ce2710277, status=NOT_RECOMMENDED}",
      "{averageAnswerTime=0.0, finalScore=1.4, totalNotAnswered=228, totalComplains=287, consumerScore=1.81, created=2025-04-27T10:04:09, start=2024-01-01T00:00:00, solvedPercentual=15.3, type=LAST_YEAR, totalAnswered=0, totalComplains30=450, averageAnswerTime3M=319290.0, hasStamp=false, dealAgainPercentual=18.6, totalEvaluated=59, answeredPercentual=0.0, company=YrngerqO28rR2QX4, end=2024-12-31T23:59:59, id=7aaebeac-83f9-4021-956d-d3ffa71cd69e, status=NOT_RECOMMENDED}",
      "{averageAnswerTime=0.0, finalScore=0.0, totalNotAnswered=0, totalComplains=0, consumerScore=0.0, created=2025-04-27T10:04:09, start=2023-01-01T00:00:00, solvedPercentual=0.0, type=PAST_LAST_YEAR, totalAnswered=0, totalComplains30=450, averageAnswerTime3M=319290.0, hasStamp=false, dealAgainPercentual=0.0, totalEvaluated=0, answeredPercentual=0.0, company=YrngerqO28rR2QX4, end=2023-12-31T23:59:59, id=b53b1aac-02ff-41a3-9026-226a7825a8b9, status=NO_INDEX}",
      "{averageAnswerTime=319290.0, finalScore=1.3, totalNotAnswered=931, totalComplains=1087, consumerScore=1.59, created=2025-04-27T10:04:09, start=2022-04-28T00:00:00, solvedPercentual=17.3, type=LAST_THREE_YEARS, totalAnswered=1, totalComplains30=450, averageAnswerTime3M=319290.0, hasStamp=false, dealAgainPercentual=16.7, totalEvaluated=156, answeredPercentual=0.1, company=YrngerqO28rR2QX4, end=2025-04-27T23:59:59, id=6c682abc-d13b-4097-ae9a-caa54dfa3f31, status=NOT_RECOMMENDED}"
    ],
    "status": "PENDING",
    "companyShortname": "cacau-show_1495770",
    "userCity": "São Paulo",
    "indexable": null,
    "description": "Comprei um ovo de Páscoa  da La Creme na loja de Bertioga quando abri vi que veio sem os bombons .liguei na loja e elas me falaram",
    "phones": null,
    "title": "Ovo de Páscoa",
    "interactions": [],
    "complainOrigin": null,
    "firstInteractionDate": null,
    "hasReply": false,
    "compliment": false,
    "legacyId": 215726627,
    "company": "YrngerqO28rR2QX4",
    "userEmail": "****",
    "productType": null,
    "address": "****",
    "canBeEvaluated": null,
    "userName": "****",
    "url": "ovo-de-pascoa_v3KKPjpqplv8HQOO",
    "inModeration": false,
    "moderateRequested": null,
    "deleted": false,
    "complainMediaInfos": [],
    "fantasyName": "Cacau Show",
    "category": null,
    "descriptionMasked": null,
    "user": null
  },
  {
    "lastReplyOrigin": null,
    "oldComplainId": null,
    "additionalFields": null,
    "moderationUserName": "****",
    "companyName": "Casas Bahia - Lojas Físicas",
    "otherProblemType": null,
    "solved": false,
    "dealAgain": null,
    "otherProductType": null,
    "titleMasked": "Atraso na entrega",
    "type": null,
    "evaluation": null,
    "score": null,
    "userState": "RJ",
    "userRequestedDelete": false,
    "requesterName": null,
    "additionalInfo": "",
    "modified": "2025-04-27T17:19:25",
    "logo": null,
    "id": "krL4A-FqjNDNZm5S",
    "evaluated": false,
    "presence": null,
    "publishedEmailSent": null,
    "deletionReason": "****",
    "read": true,
    "marketplaceComplain": null,
    "created": "2025-04-27T17:19:14",
    "maskingStatus": "MASKED",
    "ip": "****",
    "moderationReasonDescription": "****",
    "frozen": false,
    "requestEvaluation": null,
    "moderateReason": null,
    "deletedDate": null,
    "files": null,
    "problemType": "0000000000000001",
    "deletedIp": "****",
    "companyIndexes": [
      "{averageAnswerTime=1702909.2367325702, finalScore=6.6, totalNotAnswered=290, totalComplains=8108, consumerScore=4.74, created=2025-04-27T00:21:06, start=2024-10-01T00:00:00, solvedPercentual=75.6, type=SIX_MONTHS, totalAnswered=7688, totalComplains30=1245, averageAnswerTime3M=1795468.6523468576, hasStamp=false, dealAgainPercentual=49.7, totalEvaluated=3112, answeredPercentual=94.8, company=3335, end=2025-03-31T23:59:59, id=39199d27-0e9c-4f57-9ffa-63902793db82, status=REGULAR}",
      "{averageAnswerTime=1227135.62852452, finalScore=7.0, totalNotAnswered=290, totalComplains=14438, consumerScore=5.32, created=2025-04-27T00:21:06, start=2024-04-01T00:00:00, solvedPercentual=78.8, type=TWELVE_MONTHS, totalAnswered=14009, totalComplains30=1245, averageAnswerTime3M=1795468.6523468576, hasStamp=false, dealAgainPercentual=53.4, totalEvaluated=6518, answeredPercentual=97.0, company=3335, end=2025-03-31T23:59:59, id=59f4b1bf-21eb-4421-b9db-d03b50092474, status=GOOD}",
      "{averageAnswerTime=949457.7893700787, finalScore=7.2, totalNotAnswered=12, totalComplains=13273, consumerScore=5.72, created=2025-04-27T00:21:06, start=2024-01-01T00:00:00, solvedPercentual=80.6, type=LAST_YEAR, totalAnswered=13208, totalComplains30=1245, averageAnswerTime3M=1795468.6523468576, hasStamp=false, dealAgainPercentual=56.0, totalEvaluated=6571, answeredPercentual=99.5, company=3335, end=2024-12-31T23:59:59, id=349dcc0d-fc7c-4d46-89e1-df6a7eafa449, status=GOOD}",
      "{averageAnswerTime=1085821.0650844364, finalScore=8.0, totalNotAnswered=0, totalComplains=10973, consumerScore=6.87, created=2025-04-27T00:21:06, start=2023-01-01T00:00:00, solvedPercentual=89.2, type=PAST_LAST_YEAR, totalAnswered=10955, totalComplains30=1245, averageAnswerTime3M=1795468.6523468576, hasStamp=false, dealAgainPercentual=63.6, totalEvaluated=5457, answeredPercentual=99.8, company=3335, end=2023-12-31T23:59:59, id=ced462e3-b765-4a5a-a98c-0cb57be7180e, status=GREAT}",
      "{averageAnswerTime=1171029.0872737637, finalScore=7.5, totalNotAnswered=984, totalComplains=36229, consumerScore=6.17, created=2025-04-27T00:21:06, start=2022-04-28T00:00:00, solvedPercentual=84.1, type=LAST_THREE_YEARS, totalAnswered=35085, totalComplains30=1245, averageAnswerTime3M=1795468.6523468576, hasStamp=false, dealAgainPercentual=59.2, totalEvaluated=16129, answeredPercentual=96.8, company=3335, end=2025-04-27T23:59:59, id=0ec6c668-ccac-4ccb-a9e1-7945565f25ee, status=GOOD}"
    ],
    "status": "PENDING",
    "companyShortname": "casas-bahia-lojas-fisicas",
    "userCity": "Nova Iguaçu",
    "indexable": null,
    "description": "Fiz o pedido mas casa Bahia em ***** e minha encomenda já está em atraso 2 semanas e comprei o produto especificamente por causa d",
    "phones": null,
    "title": "Atraso na entrega",
    "interactions": [],
    "complainOrigin": null,
    "firstInteractionDate": null,
    "hasReply": false,
    "compliment": false,
    "legacyId": 215726625,
    "company": "3335",
    "userEmail": "****",
    "productType": "0000000000000187",
    "address": "****",
    "canBeEvaluated": null,
    "userName": "****",
    "url": "atraso-na-entrega_krL4A-FqjNDNZm5S",
    "inModeration": false,
    "moderateRequested": null,
    "deleted": false,
    "complainMediaInfos": [],
    "fantasyName": "Casas Bahia - Lojas Físicas",
    "category": "0000000000000000",
    "descriptionMasked": "Fiz o pedido mas casa Bahia em ***** e minha encomenda já está em atraso 2 semanas e comprei o produto especificamente por causa da entrega rápida, comprei no dia 16/04/25 e a entrega era para o dia 19/04/25, e hoje já são dia 27/04/25 e minha compra não foi entregue",
    "user": null
  }
]
